openEPhys_DACQ/CameraRPiController.py
openEPhys_DACQ/CameraSettings.py
openEPhys_DACQ/CumulativePosPlot.py
openEPhys_DACQ/GlobalClock.py
openEPhys_DACQ/HelperFunctions.py
openEPhys_DACQ/KlustaKwikWrapper.py
openEPhys_DACQ/NWBio.py
openEPhys_DACQ/Processing.py
openEPhys_DACQ/RPiInterface.py
openEPhys_DACQ/RecordingManager.py
openEPhys_DACQ/TaskSettings.py
openEPhys_DACQ/TrackingDataProcessing.py
openEPhys_DACQ/ZMQcomms.py
openEPhys_DACQ/__init__.py
openEPhys_DACQ/audioSignalGenerator.py
openEPhys_DACQ/createAxonaData.py
openEPhys_DACQ/displayLFPs.py
openEPhys_DACQ/milkFeederController.py
openEPhys_DACQ/package_configuration.py
openEPhys_DACQ/pelletFeederController.py
openEPhys_DACQ/sshScripts.py
openEPhys_DACQ/tracking.py
openEPhys_DACQ/video_io.py
openEPhys_DACQ/Scripts/__init__.py
openEPhys_DACQ/Scripts/annotate_video.py
openEPhys_DACQ/Scripts/h264_to_mjpeg.py
openEPhys_DACQ/Scripts/jpg_to_mp4.py
openEPhys_DACQ/Tasks/__init__.py
openEPhys_DACQ/Tasks/Pellets_and_Rep_Milk/LogParser.py
openEPhys_DACQ/Tasks/Pellets_and_Rep_Milk/Task.py
openEPhys_DACQ/Tasks/Pellets_and_Rep_Milk/__init__.py
openEPhys_DACQ/Utils/SetFileBase.set
openEPhys_DACQ/Utils/StartWebcamStream.sh
openEPhys_DACQ/Utils/KiloSortScripts/StandardConfig.m
openEPhys_DACQ/Utils/KiloSortScripts/add_kilosort_paths.m
openEPhys_DACQ/Utils/KiloSortScripts/chanMap64.mat
openEPhys_DACQ/Utils/KiloSortScripts/createChannelMap.m
openEPhys_DACQ/Utils/KiloSortScripts/master_file.m
openEPhys_DACQ-0.88.2.dist-info/LICENSE.txt
openEPhys_DACQ-0.88.2.dist-info/METADATA
openEPhys_DACQ-0.88.2.dist-info/WHEEL
openEPhys_DACQ-0.88.2.dist-info/entry_points.txt
openEPhys_DACQ-0.88.2.dist-info/top_level.txt
openEPhys_DACQ-0.88.2.dist-info/RECORD
